vsdpir_ncnn/__init__.py
vsdpir_ncnn/__main__.py
vsdpir_ncnn/drunet_color.bin
vsdpir_ncnn/drunet_color.param
vsdpir_ncnn/drunet_deblocking_color.bin
vsdpir_ncnn/drunet_deblocking_color.param
vsdpir_ncnn/drunet_deblocking_gray.bin
vsdpir_ncnn/drunet_deblocking_gray.param
vsdpir_ncnn/drunet_gray.bin
vsdpir_ncnn/drunet_gray.param
vsdpir_ncnn-2.0.0.dist-info/METADATA
vsdpir_ncnn-2.0.0.dist-info/WHEEL
vsdpir_ncnn-2.0.0.dist-info/licenses/LICENSE
vsdpir_ncnn-2.0.0.dist-info/RECORD
