Metadata-Version: 2.1
Name: vsdpir_ncnn
Version: 2.0.0
Summary: DPIR function for VapourSynth
Project-URL: Homepage, https://github.com/HolyWu/vs-dpir-ncnn
Project-URL: Bug Tracker, https://github.com/HolyWu/vs-dpir-ncnn/issues
Author-email: HolyWu <holywu@gmail.com>
License: MIT License
License-File: LICENSE
Keywords: DPIR,VapourSynth,Vulkan,ncnn
Classifier: License :: OSI Approved :: MIT License
Classifier: Operating System :: OS Independent
Classifier: Programming Language :: Python :: 3.10
Classifier: Topic :: Multimedia :: Video
Requires-Python: >=3.10
Requires-Dist: numpy
Requires-Dist: requests
Requires-Dist: tqdm
Requires-Dist: vapoursynth>=55
Requires-Dist: vsutil
